elementpath/__init__.py
elementpath/_typing.py
elementpath/aliases.py
elementpath/collations.py
elementpath/compare.py
elementpath/decoder.py
elementpath/etree.py
elementpath/exceptions.py
elementpath/helpers.py
elementpath/namespaces.py
elementpath/protocols.py
elementpath/py.typed
elementpath/schema_proxy.py
elementpath/sequence_types.py
elementpath/serialization.py
elementpath/tdop.py
elementpath/tree_builders.py
elementpath/xpath3.py
elementpath/xpath_context.py
elementpath/xpath_nodes.py
elementpath/xpath_selectors.py
elementpath/xpath_tokens.py
elementpath/datatypes/__init__.py
elementpath/datatypes/atomic_types.py
elementpath/datatypes/binary.py
elementpath/datatypes/datetime.py
elementpath/datatypes/numeric.py
elementpath/datatypes/proxies.py
elementpath/datatypes/qname.py
elementpath/datatypes/string.py
elementpath/datatypes/untyped.py
elementpath/datatypes/uri.py
elementpath/regex/__init__.py
elementpath/regex/character_classes.py
elementpath/regex/codepoints.py
elementpath/regex/patterns.py
elementpath/regex/unicode_blocks.py
elementpath/regex/unicode_categories.py
elementpath/regex/unicode_subsets.py
elementpath/validators/__init__.py
elementpath/validators/analyze-string.xsd
elementpath/validators/schema-for-json.xsd
elementpath/xpath1/__init__.py
elementpath/xpath1/_xpath1_axes.py
elementpath/xpath1/_xpath1_functions.py
elementpath/xpath1/_xpath1_operators.py
elementpath/xpath1/xpath1_parser.py
elementpath/xpath2/__init__.py
elementpath/xpath2/_xpath2_constructors.py
elementpath/xpath2/_xpath2_functions.py
elementpath/xpath2/_xpath2_operators.py
elementpath/xpath2/xpath2_parser.py
elementpath/xpath30/__init__.py
elementpath/xpath30/_translation_maps.py
elementpath/xpath30/_xpath30_functions.py
elementpath/xpath30/_xpath30_operators.py
elementpath/xpath30/xpath30_helpers.py
elementpath/xpath30/xpath30_parser.py
elementpath/xpath31/__init__.py
elementpath/xpath31/_xpath31_functions.py
elementpath/xpath31/_xpath31_operators.py
elementpath-4.6.0.dist-info/LICENSE
elementpath-4.6.0.dist-info/METADATA
elementpath-4.6.0.dist-info/WHEEL
elementpath-4.6.0.dist-info/top_level.txt
elementpath-4.6.0.dist-info/RECORD
