Metadata-Version: 2.1
Name: elementpath
Version: 4.6.0
Summary: XPath 1.0/2.0/3.0/3.1 parsers and selectors for ElementTree and lxml
Home-page: https://github.com/sissaschool/elementpath
Author: Davide Brunato
Author-email: brunato@sissa.it
License: MIT
Keywords: XPath,XPath2,XPath3,XPath31,Pratt-parser,ElementTree,lxml
Classifier: Development Status :: 5 - Production/Stable
Classifier: Intended Audience :: Developers
Classifier: Intended Audience :: Information Technology
Classifier: Intended Audience :: Science/Research
Classifier: License :: OSI Approved :: MIT License
Classifier: Operating System :: OS Independent
Classifier: Programming Language :: Python
Classifier: Programming Language :: Python :: 3
Classifier: Programming Language :: Python :: 3 :: Only
Classifier: Programming Language :: Python :: 3.8
Classifier: Programming Language :: Python :: 3.9
Classifier: Programming Language :: Python :: 3.10
Classifier: Programming Language :: Python :: 3.11
Classifier: Programming Language :: Python :: 3.12
Classifier: Programming Language :: Python :: 3.13
Classifier: Programming Language :: Python :: 3.14
Classifier: Programming Language :: Python :: Implementation :: CPython
Classifier: Programming Language :: Python :: Implementation :: PyPy
Classifier: Topic :: Software Development :: Libraries
Classifier: Topic :: Text Processing :: Markup :: XML
Requires-Python: >=3.8
License-File: LICENSE
Provides-Extra: dev
Requires-Dist: tox; extra == "dev"
Requires-Dist: coverage; extra == "dev"
Requires-Dist: lxml; extra == "dev"
Requires-Dist: xmlschema>=3.3.2; extra == "dev"
Requires-Dist: Sphinx; extra == "dev"
Requires-Dist: memory-profiler; extra == "dev"
Requires-Dist: memray; extra == "dev"
Requires-Dist: flake8; extra == "dev"
Requires-Dist: mypy; extra == "dev"
Requires-Dist: lxml-stubs; extra == "dev"
